tesspy/__init__.py
tesspy/poi_data.py
tesspy/tessellation.py
tesspy/tessellation_functions.py
tests/__init__.py
tests/test_poi_data.py
tests/test_tessellation.py
tests/test_tessellation_functions.py
tesspy-0.1.2.dist-info/LICENSE.md
tesspy-0.1.2.dist-info/METADATA
tesspy-0.1.2.dist-info/WHEEL
tesspy-0.1.2.dist-info/top_level.txt
tesspy-0.1.2.dist-info/RECORD
