Metadata-Version: 2.1
Name: tesspy
Version: 0.1.2
Summary: Tessellation of Urban Areas
Home-page: https://github.com/siavash-saki/tesspy
Author: tesspy Developers
Author-email: jonas.hamann@fb3.fra-uas.de
Classifier: Programming Language :: Python :: 3.7
Classifier: Programming Language :: Python :: 3.8
Classifier: Programming Language :: Python :: 3.9
Classifier: Programming Language :: Python :: 3.10
Classifier: License :: OSI Approved :: BSD License
Classifier: Intended Audience :: Science/Research
Classifier: Operating System :: OS Independent
Classifier: Topic :: Scientific/Engineering :: GIS
Requires-Python: >=3.7
License-File: LICENSE.md
